terrajinja/imports/vcd/__init__.py
terrajinja/imports/vcd/py.typed
terrajinja/imports/vcd/_jsii/__init__.py
terrajinja/imports/vcd/_jsii/vcd@0.0.0.jsii.tgz
terrajinja/imports/vcd/api_filter/__init__.py
terrajinja/imports/vcd/api_token/__init__.py
terrajinja/imports/vcd/catalog/__init__.py
terrajinja/imports/vcd/catalog_access_control/__init__.py
terrajinja/imports/vcd/catalog_item/__init__.py
terrajinja/imports/vcd/catalog_media/__init__.py
terrajinja/imports/vcd/catalog_vapp_template/__init__.py
terrajinja/imports/vcd/cloned_vapp/__init__.py
terrajinja/imports/vcd/cse_kubernetes_cluster/__init__.py
terrajinja/imports/vcd/data_vcd_api_filter/__init__.py
terrajinja/imports/vcd/data_vcd_catalog/__init__.py
terrajinja/imports/vcd/data_vcd_catalog_access_control/__init__.py
terrajinja/imports/vcd/data_vcd_catalog_item/__init__.py
terrajinja/imports/vcd/data_vcd_catalog_media/__init__.py
terrajinja/imports/vcd/data_vcd_catalog_vapp_template/__init__.py
terrajinja/imports/vcd/data_vcd_cse_kubernetes_cluster/__init__.py
terrajinja/imports/vcd/data_vcd_dse_registry_configuration/__init__.py
terrajinja/imports/vcd/data_vcd_dse_solution_publish/__init__.py
terrajinja/imports/vcd/data_vcd_edgegateway/__init__.py
terrajinja/imports/vcd/data_vcd_external_endpoint/__init__.py
terrajinja/imports/vcd/data_vcd_external_network/__init__.py
terrajinja/imports/vcd/data_vcd_external_network_v2/__init__.py
terrajinja/imports/vcd/data_vcd_global_role/__init__.py
terrajinja/imports/vcd/data_vcd_independent_disk/__init__.py
terrajinja/imports/vcd/data_vcd_ip_space/__init__.py
terrajinja/imports/vcd/data_vcd_ip_space_custom_quota/__init__.py
terrajinja/imports/vcd/data_vcd_ip_space_ip_allocation/__init__.py
terrajinja/imports/vcd/data_vcd_ip_space_uplink/__init__.py
terrajinja/imports/vcd/data_vcd_lb_app_profile/__init__.py
terrajinja/imports/vcd/data_vcd_lb_app_rule/__init__.py
terrajinja/imports/vcd/data_vcd_lb_server_pool/__init__.py
terrajinja_imports_vcd-3.14.1.dist-info/LICENSE
terrajinja_imports_vcd-3.14.1.dist-info/METADATA
terrajinja_imports_vcd-3.14.1.dist-info/WHEEL
terrajinja_imports_vcd-3.14.1.dist-info/top_level.txt
terrajinja_imports_vcd-3.14.1.dist-info/RECORD
